MANIFEST.in
README.rst
requirements.txt
setup.py
aiohttp_r3/__init__.py
aiohttp_r3/_r3.pyx
aiohttp_r3/cr3.pxd
aiohttp_r3/router.py
aiohttp_r3.egg-info/PKG-INFO
aiohttp_r3.egg-info/SOURCES.txt
aiohttp_r3.egg-info/dependency_links.txt
aiohttp_r3.egg-info/requires.txt
aiohttp_r3.egg-info/top_level.txt
deps/r3/.gitignore
deps/r3/.travis.yml
deps/r3/CHANGES.md
deps/r3/CMakeLists.txt
deps/r3/COPYING
deps/r3/HACKING.md
deps/r3/INSTALL
deps/r3/LICENSE
deps/r3/Makefile
deps/r3/Makefile.am
deps/r3/Makefile.in
deps/r3/README.md
deps/r3/aclocal.m4
deps/r3/autogen.sh
deps/r3/bench.html
deps/r3/bench_str.csv
deps/r3/compile
deps/r3/config.guess
deps/r3/config.h
deps/r3/config.h.in
deps/r3/config.log
deps/r3/config.status
deps/r3/config.sub
deps/r3/configure
deps/r3/configure.ac
deps/r3/depcomp
deps/r3/gen_route_tests.rb
deps/r3/gen_routes.rb
deps/r3/install-sh
deps/r3/libtool
deps/r3/ltmain.sh
deps/r3/missing
deps/r3/package.json
deps/r3/r3.pc
deps/r3/r3.pc.in
deps/r3/run-benchmark
deps/r3/stamp-h1
deps/r3/test-driver
deps/r3/3rdparty/CMakeLists.txt
deps/r3/3rdparty/Makefile
deps/r3/3rdparty/Makefile.am
deps/r3/3rdparty/Makefile.in
deps/r3/3rdparty/zmalloc.c
deps/r3/3rdparty/zmalloc.h
deps/r3/3rdparty/.deps/libr3ext_la-zmalloc.Plo
deps/r3/autom4te.cache/output.0
deps/r3/autom4te.cache/output.1
deps/r3/autom4te.cache/requests
deps/r3/autom4te.cache/traces.0
deps/r3/autom4te.cache/traces.1
deps/r3/cmake/FindCheck.cmake
deps/r3/cmake/FindJemalloc.cmake
deps/r3/cmake/FindJudy.cmake
deps/r3/cmake/FindPCRE.cmake
deps/r3/dist-debian/changelog
deps/r3/dist-debian/compat
deps/r3/dist-debian/control
deps/r3/dist-debian/copyright
deps/r3/dist-debian/docs
deps/r3/dist-debian/libr3-dev.dirs
deps/r3/dist-debian/libr3-dev.install
deps/r3/dist-debian/libr3.dirs
deps/r3/dist-debian/libr3.install
deps/r3/dist-debian/rules
deps/r3/dist-debian/source/format
deps/r3/examples/Makefile
deps/r3/examples/Makefile.am
deps/r3/examples/Makefile.in
deps/r3/examples/routing.c
deps/r3/examples/simple
deps/r3/examples/simple.c
deps/r3/examples/simple_cpp
deps/r3/examples/simple_cpp.cpp
deps/r3/examples/.deps/simple.Po
deps/r3/examples/.deps/simple_cpp.Po
