Metadata-Version: 1.0
Name: aiohttp-r3
Version: 0.0.2
Summary: R3 router for aiohttp
Home-page: https://github.com/iceb0y/aiohttp-r3
Author: iceboy
Author-email: me@iceboy.org
License: Apache 2
Platform: UNKNOWN
